pyalert/__init__.py
pyalert/pyalert.py
pyalert/utils.py
pyalert-0.0.2.dist-info/LICENSE
pyalert-0.0.2.dist-info/METADATA
pyalert-0.0.2.dist-info/WHEEL
pyalert-0.0.2.dist-info/top_level.txt
pyalert-0.0.2.dist-info/RECORD
