Metadata-Version: 2.1
Name: pyalert
Version: 0.0.2
Summary: a framework to help you stay on top of what data is flowing through your code.
Author: Sonny George
Author-email: <sonnygeorge5@gmail.com>
Keywords: python,runtime,alerts
Classifier: Intended Audience :: Developers
Classifier: Programming Language :: Python :: 3
Classifier: Operating System :: Unix
Classifier: Operating System :: MacOS :: MacOS X
Classifier: Operating System :: Microsoft :: Windows
License-File: LICENSE
